printListModule.py
setup.py
printListModuleAshwin.egg-info/PKG-INFO
printListModuleAshwin.egg-info/SOURCES.txt
printListModuleAshwin.egg-info/dependency_links.txt
printListModuleAshwin.egg-info/top_level.txt