Metadata-Version: 1.0
Name: printListModuleAshwin
Version: 1.0.0
Summary: an API to print list recursively
Home-page: UNKNOWN
Author: Ashwin
Author-email: ashwin.joseph@ignitarium.com
License: UNKNOWN
Platform: UNKNOWN
